{
  "query": "眼睛",
  "query_image_url": null,
  "timestamp": "20251106_120712",
  "total_results": 20,
  "results": [
    {
      "rank": 1,
      "title": "Pin by Cecilie Borup on ▲ MIXED FAVORITES ▲ in 2025 | Photo art, Art inspiration, Visual art",
      "url": "https://www.pinterest.com/pin/2744449768959306/",
      "description": "Apr 14, 2025 - This Pin was discovered by Cecilie Borup. Discover (and save!) your own Pins on Pinterest",
      "similarity": 0.38330146043656926,
      "similarity_precise": "0.383301460436569"
    },
    {
      "rank": 2,
      "title": "Pin on Americane",
      "url": "https://www.pinterest.com/pin/10273905394433798/",
      "description": "This Pin was discovered by Sweetdemond. Discover (and save!) your own Pins on Pinterest.",
      "similarity": 0.3464412626608969,
      "similarity_precise": "0.346441262660897"
    },
    {
      "rank": 3,
      "title": "阿里云登录 - 欢迎登录阿里云，安全稳定的云计算服务平台",
      "url": "https://ram.console.aliyun.com/profile/access-keys?spm=a2c4g.11186623.nav-v2-dropdown-my-aliyun-2.d_myaliyun_2_access_keys.69fc5ff9MsqhsB",
      "description": "欢迎登录阿里云，全球领先的云计算及人工智能科技公司，阿里云为200多个国家和地区的企业、开发者和政府机构提供云计算基础服务及解决方案。阿里云云计算、安全、大数据、人工智能、企业应用、物联网等云计算服务。",
      "similarity": 0.2828353960432216,
      "similarity_precise": "0.282835396043222"
    },
    {
      "rank": 4,
      "title": "阿里云登录 - 欢迎登录阿里云，安全稳定的云计算服务平台",
      "url": "https://home.console.aliyun.com/home/dashboard/ProductAndService?spm=a2c4g.11186623.J_4VYgf18xNlTAyFFbOuOQe.d_console.69fc5ff9MsqhsB",
      "description": "欢迎登录阿里云，全球领先的云计算及人工智能科技公司，阿里云为200多个国家和地区的企业、开发者和政府机构提供云计算基础服务及解决方案。阿里云云计算、安全、大数据、人工智能、企业应用、物联网等云计算服务。",
      "similarity": 0.2828353960432216,
      "similarity_precise": "0.282835396043222"
    },
    {
      "rank": 5,
      "title": "Pin on FUTURENATURE-VIDEO",
      "url": "https://www.pinterest.com/pin/2040762328570886/",
      "description": "This Pin was discovered by Tristan. Discover (and save!) your own Pins on Pinterest.",
      "similarity": 0.27193940442680653,
      "similarity_precise": "0.271939404426807"
    },
    {
      "rank": 6,
      "title": "Pin by 7 on 3> | Photo art, Photography inspiration, Film photography",
      "url": "https://www.pinterest.com/pin/115475177941472653/",
      "description": "This Pin was discovered by 7. Discover (and save!) your own Pins on Pinterest",
      "similarity": 0.2569584184172137,
      "similarity_precise": "0.256958418417214"
    },
    {
      "rank": 7,
      "title": "Pin on type",
      "url": "https://www.pinterest.com/pin/10766486606680569/",
      "description": "This Pin was discovered by ailsa. Discover (and save!) your own Pins on Pinterest.",
      "similarity": 0.24603224182552177,
      "similarity_precise": "0.246032241825522"
    },
    {
      "rank": 8,
      "title": "Pin by Angelica Bulzinetti on tesi | Magnum photos, Christopher anderson, Art",
      "url": "https://www.pinterest.com/pin/37014028183748344/",
      "description": "This Pin was discovered by Angelica Bulzinetti. Discover (and save!) your own Pins on Pinterest",
      "similarity": 0.1930066885479215,
      "similarity_precise": "0.193006688547921"
    },
    {
      "rank": 9,
      "title": "Pin by Sophie Bai on Motion Graphics in 2025 | Motion design animation, Motion graphics design, Motion design",
      "url": "https://www.pinterest.com/pin/1477812374547294/",
      "description": "May 19, 2025 - This Pin was discovered by Sophie Bai. Discover (and save!) your own Pins on Pinterest",
      "similarity": 0.19157741898054767,
      "similarity_precise": "0.191577418980548"
    },
    {
      "rank": 10,
      "title": "Pin on Photo inspirante",
      "url": "https://www.pinterest.com/pin/12314598975390855/",
      "description": "This Pin was discovered by Chris Pages. Discover (and save!) your own Pins on Pinterest.",
      "similarity": 0.18178095808230182,
      "similarity_precise": "0.181780958082302"
    },
    {
      "rank": 11,
      "title": "Pin on Бесконечная история",
      "url": "https://www.pinterest.com/pin/17451517302111790/",
      "description": "This Pin was discovered by Elizaveta Dzutseva. Discover (and save!) your own Pins on Pinterest.",
      "similarity": 0.17896256676527472,
      "similarity_precise": "0.178962566765275"
    },
    {
      "rank": 12,
      "title": "Pin by mo on CG映像 in 2025 | Fashion poster design, Graphic design inspiration, Fashion poster",
      "url": "https://www.pinterest.com/pin/11259067813635161/",
      "description": "Jul 17, 2025 - This Pin was discovered by mo. Discover (and save!) your own Pins on Pinterest",
      "similarity": 0.1768220355600107,
      "similarity_precise": "0.176822035560011"
    },
    {
      "rank": 13,
      "title": "Pin on Doppelganger",
      "url": "https://www.pinterest.com/pin/3025924745837057/",
      "description": "May 16, 2025 - This Pin was discovered by Fabio Rubiano Orjuela. Discover (and save!) your own Pins on Pinterest",
      "similarity": 0.17472454177487257,
      "similarity_precise": "0.174724541774873"
    },
    {
      "rank": 14,
      "title": "Pin on Bees - Apivita Greece",
      "url": "https://www.pinterest.com/pin/985231164138262/",
      "description": "This Pin was discovered by Megan May Nelson. Discover (and save!) your own Pins on Pinterest.",
      "similarity": 0.17234516768026722,
      "similarity_precise": "0.172345167680267"
    },
    {
      "rank": 15,
      "title": "Leo Burnett | Cuadros de arte, Foto arte, Pinturas",
      "url": "https://www.pinterest.com/pin/2603712282128282/",
      "description": "CBB.Arq descrubrió este Pin. Descubre (y guarda) tus propios Pines en Pinterest.",
      "similarity": 0.168403558476188,
      "similarity_precise": "0.168403558476188"
    },
    {
      "rank": 16,
      "title": "Pin on images as poems",
      "url": "https://www.pinterest.com/pin/492649954464281/",
      "description": "This Pin was discovered by zenshopper X. Discover (and save!) your own Pins on Pinterest.",
      "similarity": 0.1639689913706357,
      "similarity_precise": "0.163968991370636"
    },
    {
      "rank": 17,
      "title": "Pin on Phenom",
      "url": "https://www.pinterest.com/pin/1266706140730872/",
      "description": "This Pin was discovered by G. Discover (and save!) your own Pins on Pinterest.",
      "similarity": 0.1612116242851772,
      "similarity_precise": "0.161211624285177"
    },
    {
      "rank": 18,
      "title": "Pin by RD_Sing on Идеи для фото | Weird dreams, Cool art, Photography",
      "url": "https://www.pinterest.com/pin/10133167906403435/",
      "description": "This Pin was discovered by RD_Sing. Discover (and save!) your own Pins on Pinterest",
      "similarity": 0.15780819543891617,
      "similarity_precise": "0.157808195438916"
    },
    {
      "rank": 19,
      "title": "Pin on Grafisch ontwerp",
      "url": "https://www.pinterest.com/pin/774124930648962/",
      "description": "This Pin was discovered by Brandon. Discover (and save!) your own Pins on Pinterest.",
      "similarity": 0.14451249187805643,
      "similarity_precise": "0.144512491878056"
    },
    {
      "rank": 20,
      "title": "Pin by thaís on aRT in 2025 | Photo, Historical photos, Weird dreams",
      "url": "https://www.pinterest.com/pin/99712579247101691/",
      "description": "Jun 12, 2025 - This Pin was discovered by thaís. Discover (and save!) your own Pins on Pinterest",
      "similarity": 0.14378492163903395,
      "similarity_precise": "0.143784921639034"
    }
  ]
}